notex_ai/__init__.py
notex_ai/app.py
notex_ai/config.py
notex_ai/src/Conversation.py
notex_ai/src/constants.py
notex_ai/uploads/.DS_Store
notex_ai-0.1.0.dist-info/LICENSE
notex_ai-0.1.0.dist-info/METADATA
notex_ai-0.1.0.dist-info/WHEEL
notex_ai-0.1.0.dist-info/entry_points.txt
notex_ai-0.1.0.dist-info/RECORD
